hassil/__init__.py
hassil/__main__.py
hassil/_resources.py
hassil/errors.py
hassil/expression.py
hassil/fst.py
hassil/fuzzy.py
hassil/intents.py
hassil/models.py
hassil/ngram.py
hassil/parse_expression.py
hassil/parser.py
hassil/py.typed
hassil/recognize.py
hassil/sample.py
hassil/sample_template.py
hassil/string_matcher.py
hassil/trie.py
hassil/util.py
hassil-3.2.1.dist-info/licenses/LICENSE.md
hassil-3.2.1.dist-info/METADATA
hassil-3.2.1.dist-info/WHEEL
hassil-3.2.1.dist-info/entry_points.txt
hassil-3.2.1.dist-info/top_level.txt
hassil-3.2.1.dist-info/zip-safe
hassil-3.2.1.dist-info/RECORD
