Metadata-Version: 2.4
Name: hassil
Version: 3.2.1
Summary: The Home Assistant Intent Language parser
Author-email: The Home Assistant Authors <hello@home-assistant.io>
License: Apache-2.0
Project-URL: Source Code, https://github.com/OHF-Voice/hassil
Keywords: home,assistant,intent,recognition
Platform: any
Classifier: Development Status :: 3 - Alpha
Classifier: Intended Audience :: Developers
Classifier: Topic :: Text Processing :: Linguistic
Classifier: License :: OSI Approved :: Apache Software License
Classifier: Programming Language :: Python :: 3.9
Classifier: Programming Language :: Python :: 3.10
Classifier: Programming Language :: Python :: 3.11
Classifier: Programming Language :: Python :: 3.12
Classifier: Programming Language :: Python :: 3.13
Requires-Python: >=3.9.0
License-File: LICENSE.md
Requires-Dist: PyYAML<7,>=6.0
Requires-Dist: unicode-rbnf<3,>=2.3
Provides-Extra: dev
Requires-Dist: black==25.9.0; extra == "dev"
Requires-Dist: flake8==7.3.0; extra == "dev"
Requires-Dist: mypy==1.18.2; extra == "dev"
Requires-Dist: pylint==3.2.7; extra == "dev"
Requires-Dist: pytest==8.4.2; extra == "dev"
Requires-Dist: tox==4.30.2; extra == "dev"
Requires-Dist: types-PyYAML==6.0.12.20250915; extra == "dev"
Requires-Dist: build==1.3.0; extra == "dev"
Requires-Dist: home-assistant-intents==2025.7.30; extra == "dev"
Dynamic: license-file
